Metadata-Version: 2.2
Name: d42-typing
Version: 1.0.0
Summary: .pyi typing stubs generation for d42 schemas
Home-page: https://github.com/mytestopia/d42-typing
Author: Anna
Author-email: testopia13@gmail.com
License: Apache-2.0
Classifier: License :: OSI Approved :: Apache Software License
Classifier: Programming Language :: Python :: 3.10
Classifier: Programming Language :: Python :: 3.11
Requires-Python: >=3.10
License-File: LICENSE
Requires-Dist: d42<3.0,>=2.0
Requires-Dist: jj-d42<3.0,>=2.0
Dynamic: author
Dynamic: author-email
Dynamic: classifier
Dynamic: description
Dynamic: description-content-type
Dynamic: home-page
Dynamic: license
Dynamic: requires-dist
Dynamic: requires-python
Dynamic: summary
